{
  "id": "basic_64_weiji",
  "name": "未济",
  "symbol": "☲☵",
  "sequence": 64,
  "pinyin": "weiji",
  "type": "basic",
  "core_mechanism": {
    "name": "火水未济",
    "description": "颠倒阴阳或交换资源。",
    "variants": {
      "di": {
        "name": "倒置",
        "effect": {
          "actions": [
            {
              "action": "SET_RESOURCE",
              "params": {
                "target": "SELF",
                "resource": "YIN_YANG_GAUGE",
                "value": {
                  "op": "MULTIPLY",
                  "a": "VAR_SELF_YIN_YANG_GAUGE",
                  "b": -1
                }
              }
            }
          ]
        }
      },
      "ren": {
        "name": "震用伐鬼方",
        "usage_limit": {
          "scope": "GAME",
          "count": 1,
          "reset_timing": "NEVER"
        },
        "effect": {
          "actions": [
            {
              "action": "SWAP_DISCARD_PILES",
              "params": {
                "target_a": "SELF",
                "target_b": "OPPONENT_CHOICE_SINGLE",
                "atomic": true
              }
            }
          ]
        }
      },
      "tian": {
        "name": "易位",
        "effect": {
          "actions": [
            {
              "action": "SWAP_RESOURCES",
              "params": {
                "target_a": "SELF",
                "target_b": "OPPONENT_CHOICE_SINGLE",
                "resource": "gold",
                "atomic": true
              }
            }
          ]
        }
      }
    }
  },
  "metadata": {
    "image_url": "assets/images/cards/basic/basic_64_weiji.png"
  }
}